{
    "SunShine": [
        "5.8",
        "8.2",
        "9.0",
        "8.9",
        "10.4",
        "9.3",
        "0.0",
        "0.0",
        "0.2",
        "0.0",
        "0.0",
        "0.0",
        "8.1",
        "11.2",
        "11.0",
        "9.3",
        "2.9",
        "1.8",
        "4.3",
        "2.3",
        "0.0",
        "1.3",
        "0.7",
        "2.3",
        "5.2",
        "6.4",
        "7.9",
        "2.2",
        "5.3",
        "8.1"
    ],
    "Temperature": [
        "24.2",
        "24.9",
        "25.5",
        "25.5",
        "25.4",
        "25.8",
        "17.7",
        "14.2",
        "17.3",
        "16.8",
        "15.5",
        "17.3",
        "18.4",
        "17.4",
        "19.2",
        "22.0",
        "21.5",
        "24.2",
        "25.9",
        "24.6",
        "18.1",
        "19.2",
        "23.3",
        "23.1",
        "22.8",
        "25.4",
        "24.2",
        "24.1",
        "24.8",
        "24.6"
    ],
    "SeaPres": [
        "1012.8",
        "1008.9",
        "1008.4",
        "1011.2",
        "1012.0",
        "1012.7",
        "1018.6",
        "1022.3",
        "1019.4",
        "1019.5",
        "1020.5",
        "1018.7",
        "1018.4",
        "1017.8",
        "1016.6",
        "1015.2",
        "1014.3",
        "1011.3",
        "1007.3",
        "1008.0",
        "1015.6",
        "1019.3",
        "1018.0",
        "1017.5",
        "1017.4",
        "1015.7",
        "1013.9",
        "1011.3",
        "1010.9",
        "1012.4"
    ],
    "WD": [
        "290",
        "310",
        "310",
        "300",
        "130",
        "20",
        "20",
        "20",
        "20",
        "20",
        "30",
        "10",
        "30",
        "300",
        "140",
        "300",
        "90",
        "310",
        "310",
        "300",
        "30",
        "20",
        "140",
        "10",
        "150",
        "150",
        "300",
        "300",
        "310",
        "160"
    ],
    "Precp": [
        "0.0",
        "0.0",
        "0.0",
        "0.0",
        "0.0",
        "0.0",
        "0.1",
        "8.5",
        "4.5",
        "19.5",
        "15.0",
        "5.0",
        "0.0",
        "0.0",
        "0.0",
        "0.0",
        "0.0",
        "1.0",
        "2.0",
        "19.5",
        "14.0",
        "0.5",
        "0.0",
        "0.0",
        "0.0",
        "0.0",
        "0.0",
        "0.0",
        "0.0",
        "0.0"
    ],
    "RH": [
        "83",
        "81",
        "78",
        "77",
        "80",
        "76",
        "80",
        "86",
        "85",
        "85",
        "88",
        "89",
        "67",
        "57",
        "58",
        "70",
        "85",
        "82",
        "77",
        "74",
        "83",
        "75",
        "68",
        "77",
        "68",
        "62",
        "79",
        "83",
        "80",
        "74"
    ],
    "WS": [
        "1.4",
        "1.7",
        "1.5",
        "1.4",
        "1.2",
        "2.0",
        "4.5",
        "2.8",
        "1.4",
        "2.0",
        "1.4",
        "1.2",
        "1.6",
        "2.3",
        "2.0",
        "2.0",
        "1.3",
        "1.3",
        "2.2",
        "2.7",
        "1.6",
        "1.3",
        "2.3",
        "1.3",
        "1.7",
        "2.6",
        "1.5",
        "1.4",
        "1.3",
        "1.8"
    ]
}